setup.py
shinkenplugins/__init__.py
shinkenplugins.plugins.fake.egg-info/PKG-INFO
shinkenplugins.plugins.fake.egg-info/SOURCES.txt
shinkenplugins.plugins.fake.egg-info/dependency_links.txt
shinkenplugins.plugins.fake.egg-info/entry_points.txt
shinkenplugins.plugins.fake.egg-info/namespace_packages.txt
shinkenplugins.plugins.fake.egg-info/requires.txt
shinkenplugins.plugins.fake.egg-info/top_level.txt
shinkenplugins/plugins/__init__.py
shinkenplugins/plugins/fake/__init__.py
shinkenplugins/plugins/fake/fake.py